{
  "policyProgress": "Policy and Progress",
  "employeeId": "Employee ID",
  "employee": "Employee",
  "id": "ID",
  "promotion": "Promotion",
  "tobe": "ToBe",
  "asis": "Asis",
  "tobeFY": "ToBe FY",
  "tRisk": "T-Risk",
  "status": "Status",
  "description": "Description",
  "whatShoudBe": "Assignments should be done",
  "registrationDate": "Registration Date",
  "register": "Register",
  "updateDate": "Update Date",
  "updater": "Updater",
  "name": "Name",
  "policyProgressHistory": "Policy and Progress History",
  "promotionHistoty": "Promotion History",
  "tRiskHistory": "T-Risk History",
  "year": "Fiscal Year",
  "tobe_fy": "ToBe FY Fiscal",
  "tobe_fy1": "ToBe FY Fiscal plus 1",
  "tobe_fy2": "ToBe FY Fiscal plus 2",
  "tobe_fy3": "ToBe FY Fiscal plus 3",
  "noData": "No Data",
  "tRiskSelected": "T risk (selected)",
  "tRiskDescription": "T risk (description)",
  "whatTodoAssign": "What to do in ASSIGN"
}
